README.txt
setup.cfg
setup.py
medialog/__init__.py
medialog.newsitemviews.egg-info/.DS_Store
medialog.newsitemviews.egg-info/PKG-INFO
medialog.newsitemviews.egg-info/SOURCES.txt
medialog.newsitemviews.egg-info/dependency_links.txt
medialog.newsitemviews.egg-info/entry_points.txt
medialog.newsitemviews.egg-info/namespace_packages.txt
medialog.newsitemviews.egg-info/not-zip-safe
medialog.newsitemviews.egg-info/requires.txt
medialog.newsitemviews.egg-info/top_level.txt
medialog/app/__init__.py
medialog/app/config.py
medialog/app/newsitemviews/__init__.py
medialog/app/newsitemviews/config.py
medialog/app/newsitemviews/tests.py
medialog/app/newsitemviews/browser/__init__.py
medialog/app/newsitemviews/browser/x-newsitemviews.py