Metadata-Version: 1.0
Name: medialog.newsitemviews
Version: 0.1.alphadev
Summary: More views for newsitems
Home-page: http://medialog.no/plone
Author: Espen Moe-Nilssen
Author-email: espen@medialog.no
License: GPL
Keywords: view news-item
Platform: UNKNOWN
Classifier: Framework :: Plone
Classifier: Programming Language :: Python
Classifier: Topic :: Software Development :: Libraries :: Python Modules
